run.py
trnsim/__init__.py
trnsim/base.py
trnsim/strategy.py
trading_simulator-1.0.1.dist-info/LICENSE
trading_simulator-1.0.1.dist-info/METADATA
trading_simulator-1.0.1.dist-info/WHEEL
trading_simulator-1.0.1.dist-info/top_level.txt
trading_simulator-1.0.1.dist-info/RECORD
