Metadata-Version: 2.1
Name: trading-simulator
Version: 1.0.1
Summary: Simulation on financial market transaction (eg. Stock buy&sell).
Author-email: Jingxiao Zhang <rex.zhang2016@foxmail.com>
Project-URL: Homepage, https://github.com/rexzhang2014/trn-sim
Project-URL: Bug Tracker, https://github.com/rexzhang2014/trn-sim/issues
Classifier: Programming Language :: Python :: 3
Classifier: License :: OSI Approved :: MIT License
Classifier: Operating System :: OS Independent
Requires-Python: >=3.7
License-File: LICENSE
